{"_type":"export","__export_format":4,"__export_date":"2024-02-21T11:09:25.874Z","__export_source":"insomnia.desktop.app:v8.6.1","resources":[{"_id":"req_ce53abefd6dd4eaabb21be9339e378f0","parentId":"fld_3f32330d867b4ec4a48c738129e74ee3","modified":1708512923395,"created":1708046451089,"url":"http://localhost:3000/item","name":"Create","description":"","method":"POST","body":{"mimeType":"application/json","text":"{\n\t\"id\": \"i1110\",\n\t\"nome\": \"insomnia\",\n  \"descricao\": \"funcionando\",\n  \"valor\": 201\n}"},"parameters":[],"headers":[{"name":"Content-Type","value":"application/json"},{"name":"User-Agent","value":"insomnia/8.6.1"}],"authentication":{},"metaSortKey":-1708046451089,"isPrivate":false,"pathParameters":[],"settingStoreCookies":true,"settingSendCookies":true,"settingDisableRenderRequestBody":false,"settingEncodeUrl":true,"settingRebuildPath":true,"settingFollowRedirects":"global","_type":"request"},{"_id":"fld_3f32330d867b4ec4a48c738129e74ee3","parentId":"wrk_scratchpad","modified":1708046402909,"created":1708046402909,"name":"PapelTudo","description":"","environment":{},"environmentPropertyOrder":null,"metaSortKey":-1708046402909,"_type":"request_group"},{"_id":"wrk_scratchpad","parentId":null,"modified":1706098234127,"created":1706098234127,"name":"Scratch Pad","description":"","scope":"collection","_type":"workspace"},{"_id":"req_7c26c80360fe4f11b5482c3a8e2db3bd","parentId":"fld_3f32330d867b4ec4a48c738129e74ee3","modified":1708046618307,"created":1708046444382,"url":"http://localhost:3000/item","name":"Read","description":"","method":"GET","body":{},"parameters":[],"headers":[{"name":"User-Agent","value":"insomnia/8.6.1"}],"authentication":{},"metaSortKey":-1708046444382,"isPrivate":false,"pathParameters":[],"settingStoreCookies":true,"settingSendCookies":true,"settingDisableRenderRequestBody":false,"settingEncodeUrl":true,"settingRebuildPath":true,"settingFollowRedirects":"global","_type":"request"},{"_id":"req_4f70d37324ca4629937dcd19b1449ab5","parentId":"fld_3f32330d867b4ec4a48c738129e74ee3","modified":1708513678602,"created":1708046430085,"url":"http://localhost:3000/item/i22","name":"Update","description":"","method":"PUT","body":{"mimeType":"application/json","text":"{\n\t\"id\": \"i22\",\n\t\"nome\": \"testando função\",\n\t\"descricao\": \"de calcular patrimonio\",\n\t\"valor\": 500\n}"},"parameters":[],"headers":[{"name":"Content-Type","value":"application/json"},{"name":"User-Agent","value":"insomnia/8.6.1"}],"authentication":{},"metaSortKey":-1708046430085,"isPrivate":false,"pathParameters":[],"settingStoreCookies":true,"settingSendCookies":true,"settingDisableRenderRequestBody":false,"settingEncodeUrl":true,"settingRebuildPath":true,"settingFollowRedirects":"global","_type":"request"},{"_id":"req_9551cc82531e47cc8e45d9a8b8862188","parentId":"fld_3f32330d867b4ec4a48c738129e74ee3","modified":1708513008567,"created":1708046405939,"url":"http://localhost:3000/item/i001","name":"Delete","description":"","method":"DELETE","body":{},"parameters":[],"headers":[{"name":"User-Agent","value":"insomnia/8.6.1"}],"authentication":{},"metaSortKey":-1708046405939,"isPrivate":false,"pathParameters":[],"settingStoreCookies":true,"settingSendCookies":true,"settingDisableRenderRequestBody":false,"settingEncodeUrl":true,"settingRebuildPath":true,"settingFollowRedirects":"global","_type":"request"},{"_id":"req_49715d23c8804203b220ca05af12640d","parentId":"fld_b075eb19aebb41edbf77e780ed4c7da2","modified":1708046217253,"created":1708046124259,"url":"http://localhost:3000","name":"Teste","description":"","method":"GET","body":{},"parameters":[],"headers":[{"name":"User-Agent","value":"insomnia/8.6.1"}],"authentication":{},"metaSortKey":-1708046124259,"isPrivate":false,"pathParameters":[],"settingStoreCookies":true,"settingSendCookies":true,"settingDisableRenderRequestBody":false,"settingEncodeUrl":true,"settingRebuildPath":true,"settingFollowRedirects":"global","_type":"request"},{"_id":"fld_b075eb19aebb41edbf77e780ed4c7da2","parentId":"wrk_scratchpad","modified":1708046091500,"created":1708046091500,"name":"Teste","description":"","environment":{},"environmentPropertyOrder":null,"metaSortKey":-1708046091500,"_type":"request_group"},{"_id":"env_99d30891da4bdcebc63947a8fc17f076de878684","parentId":"wrk_scratchpad","modified":1707390616784,"created":1707390616784,"name":"Base Environment","data":{},"dataPropertyOrder":null,"color":null,"isPrivate":false,"metaSortKey":1707390616784,"_type":"environment"},{"_id":"jar_99d30891da4bdcebc63947a8fc17f076de878684","parentId":"wrk_scratchpad","modified":1707390616792,"created":1707390616792,"name":"Default Jar","cookies":[],"_type":"cookie_jar"}]}